pz_rail_sompz-0.0.3.dist-info/licenses/LICENSE
rail/estimation/algos/cellmap.py
rail/estimation/algos/som.py
rail/estimation/algos/sompz.py
rail/examples_data/estimation_data/configs/test_sompz.columns
rail/pipelines/estimation/estimate_sompz.py
rail/pipelines/estimation/inform_sompz.py
rail/sompz/__init__.py
rail/sompz/__init__.py~
rail/sompz/_version.py
rail/sompz/utils.py
rail/sompz/utils.py~
pz_rail_sompz-0.0.3.dist-info/METADATA
pz_rail_sompz-0.0.3.dist-info/WHEEL
pz_rail_sompz-0.0.3.dist-info/top_level.txt
pz_rail_sompz-0.0.3.dist-info/RECORD
