Metadata-Version: 2.4
Name: pz-rail-sompz
Version: 0.0.3
Author-email: LSST DESC PZ WG <samuel.j.schmidt@gmail.com>
License: MIT License
Classifier: Development Status :: 4 - Beta
Classifier: License :: OSI Approved :: MIT License
Classifier: Intended Audience :: Developers
Classifier: Intended Audience :: Science/Research
Classifier: Operating System :: OS Independent
Classifier: Programming Language :: Python
License-File: LICENSE
Requires-Dist: numba
Requires-Dist: pz-rail-base>=1.0.3
Requires-Dist: qp-prob[full]
Requires-Dist: tqdm
Provides-Extra: dev
Requires-Dist: pytest; extra == "dev"
Requires-Dist: pytest-cov; extra == "dev"
Requires-Dist: pre-commit; extra == "dev"
Requires-Dist: pylint; extra == "dev"
Dynamic: license-file
